asyncVK/__init__.py
asyncVK/chain.py
asyncVK/condition.py
asyncVK/dispatcher.py
asyncVK/handlers.py
asyncVK/core/__init__.py
asyncVK/core/keyboard.py
asyncVK/core/message.py
asyncVK/core/types.py
asyncVK/sync/__init__.py
upload/__init__.py
async_VKsher-2.3.0.dist-info/LICENSE
async_VKsher-2.3.0.dist-info/METADATA
async_VKsher-2.3.0.dist-info/WHEEL
async_VKsher-2.3.0.dist-info/top_level.txt
async_VKsher-2.3.0.dist-info/RECORD
