Metadata-Version: 2.2
Name: async_VKsher
Version: 2.3.0
Summary: asyncVK is asynchronous library for creating a bot in VK
Home-page: https://github.com/Ekventor/asyncVK
Author: Kulenov Islam
Author-email: kit.werr34@gmail.com
Keywords: vk vkontakte вк вконтакте бот bot api vk_api
Classifier: Programming Language :: Python :: 3.12
Classifier: License :: OSI Approved :: GNU General Public License v3 (GPLv3)
License-File: LICENSE
Requires-Dist: asyncio>=3
Requires-Dist: aiohttp>=3
Dynamic: author
Dynamic: author-email
Dynamic: classifier
Dynamic: description
Dynamic: description-content-type
Dynamic: home-page
Dynamic: keywords
Dynamic: requires-dist
Dynamic: summary
